LICENSE
Readme.md
pyproject.toml
setup.cfg
setup.py
src/seano_formatter_semver/__init__.py
src/seano_formatter_semver/semver.py
src/seano_formatter_semver.egg-info/PKG-INFO
src/seano_formatter_semver.egg-info/SOURCES.txt
src/seano_formatter_semver.egg-info/dependency_links.txt
src/seano_formatter_semver.egg-info/top_level.txt